elixirdb/__about__.py
elixirdb/__init__.py
elixirdb/base.py
elixirdb/enums.py
elixirdb/exc.py
elixirdb/py.typed
elixirdb/types.py
elixirdb/core/__init__.py
elixirdb/core/db.py
elixirdb/core/handlers.py
elixirdb/dictionaries/__init__.py
elixirdb/dictionaries/db_errors.py
elixirdb/dictionaries/model_fields.py
elixirdb/dictionaries/resources.py
elixirdb/models/engine.py
elixirdb/models/manager.py
elixirdb/models/meta.py
elixirdb/models/model.py
elixirdb/models/options.py
elixirdb/models/schemas.py
elixirdb/models/urls.py
elixirdb/models/validator.py
elixirdb/utils/__init__.py
elixirdb/utils/db_utils.py
elixirdb/utils/files.py
elixirdb/utils/formatters.py
elixirdb/utils/wrappers.py
elixirdb-0.14.dist-info/METADATA
elixirdb-0.14.dist-info/WHEEL
elixirdb-0.14.dist-info/top_level.txt
elixirdb-0.14.dist-info/RECORD
