Metadata-Version: 2.2
Name: elixirdb
Version: 0.14
Summary: A python library for a streamlined database experience from a config file.
Author-email: Victor Nguyen <victor.win86@gmail.com>
License: MIT
Project-URL: homepage, https://github.com/hotnsoursoup/elixir-db
Project-URL: documentation, https://github.com/hotnsoursoup/elixir-db/tree/master/docs
Project-URL: testing, https://github.com/hotnsoursoup/elixir-db/blob/master/docs/tests.md
Keywords: database,SQL,config,ORM,streamlined
Classifier: License :: OSI Approved :: MIT License
Classifier: Operating System :: OS Independent
Classifier: Programming Language :: Cython
Classifier: Programming Language :: Python
Classifier: Programming Language :: Python :: 3
Classifier: Programming Language :: Python :: 3 :: Only
Classifier: Programming Language :: Python :: 3.11
Classifier: Programming Language :: Python :: 3.12
Classifier: Programming Language :: Python :: 3.13
Classifier: Topic :: Database
Requires-Python: >=3.12
Requires-Dist: pydantic<3.0.0,>=2.9.1
Requires-Dist: SQLAlchemy>=2.0.34
Requires-Dist: sqlparse>=0.5.1
Requires-Dist: sqlglot>=25.29.0
Requires-Dist: python-dateutil>=2.8.2
Requires-Dist: pyrootutils>=1.0.4
Requires-Dist: sqlalchemy-mixins>=2.0.5
Requires-Dist: pyaml>=25.1.0
Provides-Extra: mysql
Requires-Dist: pymysql>=1.1.1; extra == "mysql"
Provides-Extra: mariadb
Requires-Dist: mariadb; extra == "mariadb"
Provides-Extra: postgresql
Requires-Dist: psycopg2>=2.9.6; extra == "postgresql"
Provides-Extra: mssql
Requires-Dist: pymssql>=2.2.0; extra == "mssql"
Provides-Extra: oracle
Requires-Dist: oracledb>=2.3.0; extra == "oracle"
Provides-Extra: all-dbs
Requires-Dist: psycopg2>=2.9.6; extra == "all-dbs"
Requires-Dist: pymssql>=2.2.2; extra == "all-dbs"
Requires-Dist: oracledb>=2.3.0; extra == "all-dbs"
Requires-Dist: mariadb; extra == "all-dbs"
Provides-Extra: test
Requires-Dist: pyaml-env>=1.2.1; extra == "test"
Requires-Dist: pytest-timeout>=2.3.1; extra == "test"
Requires-Dist: pytest>=8.3.3; extra == "test"
Requires-Dist: pytest-asyncio>=0.25.0; extra == "test"
Requires-Dist: pytest-html>=4.1.1; extra == "test"
Requires-Dist: pytest-order>=1.3.0; extra == "test"
Provides-Extra: all
Requires-Dist: pymysql>=1.1.1; extra == "all"
Requires-Dist: psycopg2>=2.9.6; extra == "all"
Requires-Dist: pymssql>=2.2.2; extra == "all"
Requires-Dist: oracledb>=2.3.0; extra == "all"
Requires-Dist: mariadb; extra == "all"
Requires-Dist: ruff; extra == "all"
Requires-Dist: bandit; extra == "all"
Requires-Dist: black; extra == "all"
Requires-Dist: isort; extra == "all"
Requires-Dist: pyaml-env>=1.2.1; extra == "all"
Requires-Dist: pytest>=8.3.3; extra == "all"
Requires-Dist: pytest-asyncio>=0.25.0; extra == "all"
Requires-Dist: pytest-html>=4.1.1; extra == "all"
Requires-Dist: pytest-order>=1.3.0; extra == "all"
Provides-Extra: all-dbs
Requires-Dist: pymysql>=1.1.1; extra == "all-dbs"
